{
  "version": "3.21.1",
  "flags": {},
  "shapes": [
    {
      "label": "Brick",
      "line_color": null,
      "fill_color": null,
      "points": [
        [
          997.4176635742188,
          208.54324340820312
        ],
        [
          1018.2179565429688,
          169.42364501953125
        ],
        [
          1179.082275390625,
          254.95675659179688
        ],
        [
          1159.0062111801242,
          296.2732919254658
        ]
      ],
      "shape_type": "polygon",
      "flags": {}
    },
    {
      "label": "Brick",
      "line_color": null,
      "fill_color": null,
      "points": [
        [
          827.9503105590062,
          149.68944099378882
        ],
        [
          847.2049689440993,
          110.55900621118012
        ],
        [
          1006.2791748046875,
          185.80654907226562
        ],
        [
          986.3388671875,
          226.69015502929688
        ]
      ],
      "shape_type": "polygon",
      "flags": {}
    },
    {
      "label": "Brick",
      "line_color": null,
      "fill_color": null,
      "points": [
        [
          979.4176635742188,
          250.5432586669922
        ],
        [
          1000.2179565429688,
          211.42364501953125
        ],
        [
          1161.082275390625,
          296.95672607421875
        ],
        [
          1140.281982421875,
          336.07635498046875
        ]
      ],
      "shape_type": "polygon",
      "flags": {}
    },
    {
      "label": "Brick",
      "line_color": null,
      "fill_color": null,
      "points": [
        [
          963.6630859375,
          297.2273864746094
        ],
        [
          983.08544921875,
          257.4056701660156
        ],
        [
          1146.8369140625,
          337.2726135253906
        ],
        [
          1127.41455078125,
          377.0943298339844
        ]
      ],
      "shape_type": "polygon",
      "flags": {}
    },
    {
      "label": "Brick",
      "line_color": null,
      "fill_color": null,
      "points": [
        [
          808.695652173913,
          189.44099378881987
        ],
        [
          827.9503105590062,
          150.31055900621118
        ],
        [
          989.7791748046875,
          227.80653381347656
        ],
        [
          969.8388671875,
          268.69012451171875
        ]
      ],
      "shape_type": "polygon",
      "flags": {}
    },
    {
      "label": "Brick",
      "line_color": null,
      "fill_color": null,
      "points": [
        [
          938.2207641601562,
          336.6934509277344
        ],
        [
          958.1610107421875,
          295.8098449707031
        ],
        [
          1126.279296875,
          377.8065490722656
        ],
        [
          1106.3389892578125,
          418.6901550292969
        ]
      ],
      "shape_type": "polygon",
      "flags": {}
    },
    {
      "label": "Brick",
      "line_color": null,
      "fill_color": null,
      "points": [
        [
          920.220703125,
          377.1934509277344
        ],
        [
          940.1610107421875,
          336.3098449707031
        ],
        [
          1109.3167701863354,
          422.9813664596273
        ],
        [
          1091.304347826087,
          459.62732919254654
        ]
      ],
      "shape_type": "polygon",
      "flags": {}
    },
    {
      "label": "Brick",
      "line_color": null,
      "fill_color": null,
      "points": [
        [
          849.0683229813665,
          109.3167701863354
        ],
        [
          866.4596273291925,
          69.56521739130434
        ],
        [
          1026.8369140625,
          146.77261352539062
        ],
        [
          1007.41455078125,
          186.59429931640625
        ]
      ],
      "shape_type": "polygon",
      "flags": {}
    },
    {
      "label": "Brick",
      "line_color": null,
      "fill_color": null,
      "points": [
        [
          790.6832298136645,
          229.1925465838509
        ],
        [
          809.3167701863354,
          190.68322981366458
        ],
        [
          974.3988037109375,
          263.4608459472656
        ],
        [
          955.4169921875,
          306.09478759765625
        ]
      ],
      "shape_type": "polygon",
      "flags": {}
    },
    {
      "label": "Brick",
      "line_color": null,
      "fill_color": null,
      "points": [
        [
          904.4954223632812,
          411.42437744140625
        ],
        [
          924.2236024844719,
          377.01863354037266
        ],
        [
          1088.8198757763973,
          461.4906832298136
        ],
        [
          1069.6494140625,
          499.2384033203125
        ]
      ],
      "shape_type": "polygon",
      "flags": {}
    },
    {
      "label": "Brick",
      "line_color": null,
      "fill_color": null,
      "points": [
        [
          769.5652173913043,
          269.5652173913043
        ],
        [
          788.8198757763975,
          229.81366459627327
        ],
        [
          952.2791748046875,
          307.3065490722656
        ],
        [
          932.3388671875,
          348.1901550292969
        ]
      ],
      "shape_type": "polygon",
      "flags": {}
    },
    {
      "label": "Brick",
      "line_color": null,
      "fill_color": null,
      "points": [
        [
          732.6630859375,
          345.2273864746094
        ],
        [
          752.08544921875,
          305.4056701660156
        ],
        [
          915.8369140625,
          385.2726135253906
        ],
        [
          896.41455078125,
          425.0943298339844
        ]
      ],
      "shape_type": "polygon",
      "flags": {}
    },
    {
      "label": "Brick",
      "line_color": null,
      "fill_color": null,
      "points": [
        [
          753.416149068323,
          304.96894409937886
        ],
        [
          769.5652173913043,
          268.94409937888196
        ],
        [
          935.163818359375,
          344.8744201660156
        ],
        [
          914.187744140625,
          387.8818664550781
        ]
      ],
      "shape_type": "polygon",
      "flags": {}
    },
    {
      "label": "Brick",
      "line_color": null,
      "fill_color": null,
      "points": [
        [
          1013.9176635742188,
          171.04324340820312
        ],
        [
          1034.718017578125,
          131.92364501953125
        ],
        [
          1195.582275390625,
          217.45675659179688
        ],
        [
          1174.781982421875,
          256.57635498046875
        ]
      ],
      "shape_type": "polygon",
      "flags": {}
    },
    {
      "label": "Brick",
      "line_color": null,
      "fill_color": null,
      "points": [
        [
          1028.917724609375,
          130.54324340820312
        ],
        [
          1049.718017578125,
          91.42364501953125
        ],
        [
          1210.582275390625,
          176.95675659179688
        ],
        [
          1189.781982421875,
          216.07635498046875
        ]
      ],
      "shape_type": "polygon",
      "flags": {}
    },
    {
      "label": "Brick",
      "line_color": null,
      "fill_color": null,
      "points": [
        [
          859.6273291925467,
          62.732919254658405
        ],
        [
          880.7453416149068,
          25.465838509316768
        ],
        [
          1041.3098629779697,
          105.8791073627354
        ],
        [
          1023.959338075626,
          141.45314300726665
        ]
      ],
      "shape_type": "polygon",
      "flags": {}
    }
  ],
  "lineColor": [
    0,
    255,
    0,
    128
  ],
  "fillColor": [
    255,
    0,
    0,
    128
  ],
  "imagePath": "OP_colorIMG_485.png",
  "imageData": null,
  "imageHeight": 720,
  "imageWidth": 1280
}