{
    "fillColor": [
        255,
        0,
        0,
        128
    ],
    "flags": {},
    "imageData": null,
    "imageHeight": 720,
    "imagePath": "OP_colorIMG_75.png",
    "imageWidth": 1280,
    "lineColor": [
        0,
        255,
        0,
        128
    ],
    "shapes": [
        {
            "fill_color": null,
            "flags": {},
            "label": "Brick",
            "line_color": null,
            "points": [
                [
                    714.2033081054688,
                    520.3560180664063
                ],
                [
                    708.1510620117188,
                    486.03173828125
                ],
                [
                    849.2965698242188,
                    461.14398193359375
                ],
                [
                    855.3488159179688,
                    495.46826171875
                ]
            ],
            "shape_type": "polygon"
        },
        {
            "fill_color": null,
            "flags": {},
            "label": "Brick",
            "line_color": null,
            "points": [
                [
                    707.2112426757813,
                    481.98065185546875
                ],
                [
                    702.3605346679688,
                    447.466064453125
                ],
                [
                    844.2886352539063,
                    427.51934814453125
                ],
                [
                    849.1393432617188,
                    462.033935546875
                ]
            ],
            "shape_type": "polygon"
        },
        {
            "fill_color": null,
            "flags": {},
            "label": "Brick",
            "line_color": null,
            "points": [
                [
                    569.03466796875,
                    502.5575866699219
                ],
                [
                    564.348388671875,
                    469.2129821777344
                ],
                [
                    701.46533203125,
                    449.9424133300781
                ],
                [
                    706.151611328125,
                    483.2870178222656
                ]
            ],
            "shape_type": "polygon"
        },
        {
            "fill_color": null,
            "flags": {},
            "label": "Brick",
            "line_color": null,
            "points": [
                [
                    640.6088256835938,
                    300.6560974121094
                ],
                [
                    630.2035522460938,
                    268.6318054199219
                ],
                [
                    761.8911743164063,
                    225.84390258789063
                ],
                [
                    772.2964477539063,
                    257.8681945800781
                ]
            ],
            "shape_type": "polygon"
        },
        {
            "fill_color": null,
            "flags": {},
            "label": "Brick",
            "line_color": null,
            "points": [
                [
                    702.53466796875,
                    448.5575866699219
                ],
                [
                    697.848388671875,
                    415.2129821777344
                ],
                [
                    834.96533203125,
                    395.9424133300781
                ],
                [
                    839.651611328125,
                    429.2870178222656
                ]
            ],
            "shape_type": "polygon"
        },
        {
            "fill_color": null,
            "flags": {},
            "label": "Brick",
            "line_color": null,
            "points": [
                [
                    748.9039916992188,
                    240.09454345703125
                ],
                [
                    789.2684936523438,
                    234.42169189453125
                ],
                [
                    812.5960083007813,
                    400.40545654296875
                ],
                [
                    772.2315063476563,
                    406.07830810546875
                ]
            ],
            "shape_type": "polygon"
        },
        {
            "fill_color": null,
            "flags": {},
            "label": "Brick",
            "line_color": null,
            "points": [
                [
                    597.6239624023438,
                    341.36322021484375
                ],
                [
                    591.1613159179688,
                    304.71185302734375
                ],
                [
                    741.8760375976563,
                    278.13677978515625
                ],
                [
                    748.3386840820313,
                    314.78814697265625
                ]
            ],
            "shape_type": "polygon"
        },
        {
            "fill_color": null,
            "flags": {},
            "label": "Brick",
            "line_color": null,
            "points": [
                [
                    689.9830322265625,
                    217.84036254882813
                ],
                [
                    722.3509521484375,
                    208.55899047851563
                ],
                [
                    760.5169677734375,
                    341.6596374511719
                ],
                [
                    728.1490478515625,
                    350.9410095214844
                ]
            ],
            "shape_type": "polygon"
        },
        {
            "fill_color": null,
            "flags": {},
            "label": "Brick",
            "line_color": null,
            "points": [
                [
                    569.8026733398438,
                    536.5720825195313
                ],
                [
                    566.1594848632813,
                    501.9092102050781
                ],
                [
                    708.6973266601563,
                    486.92791748046875
                ],
                [
                    712.3405151367188,
                    521.5908203125
                ]
            ],
            "shape_type": "polygon"
        }
    ],
    "version": "3.21.1"
}
