{
  "version": "3.21.1",
  "flags": {},
  "shapes": [
    {
      "label": "Brick",
      "line_color": null,
      "fill_color": null,
      "points": [
        [
          807.2320556640625,
          378.11285400390625
        ],
        [
          819.0977783203125,
          341.59393310546875
        ],
        [
          969.267822265625,
          390.38714599609375
        ],
        [
          957.402099609375,
          426.90606689453125
        ]
      ],
      "shape_type": "polygon",
      "flags": {}
    },
    {
      "label": "Brick",
      "line_color": null,
      "fill_color": null,
      "points": [
        [
          660.2249755859375,
          332.30169677734375
        ],
        [
          671.7255859375,
          296.90643310546875
        ],
        [
          817.2750244140625,
          344.19830322265625
        ],
        [
          805.7744140625,
          379.59356689453125
        ]
      ],
      "shape_type": "polygon",
      "flags": {}
    },
    {
      "label": "Brick",
      "line_color": null,
      "fill_color": null,
      "points": [
        [
          795.2320556640625,
          414.11285400390625
        ],
        [
          807.0977783203125,
          377.59393310546875
        ],
        [
          957.267822265625,
          426.38714599609375
        ],
        [
          945.402099609375,
          462.90606689453125
        ]
      ],
      "shape_type": "polygon",
      "flags": {}
    },
    {
      "label": "Brick",
      "line_color": null,
      "fill_color": null,
      "points": [
        [
          670.7321166992188,
          297.11285400390625
        ],
        [
          682.5978393554688,
          260.59393310546875
        ],
        [
          832.7678833007812,
          309.38714599609375
        ],
        [
          820.9021606445312,
          345.90606689453125
        ]
      ],
      "shape_type": "polygon",
      "flags": {}
    },
    {
      "label": "Brick",
      "line_color": null,
      "fill_color": null,
      "points": [
        [
          820.7320556640625,
          340.61285400390625
        ],
        [
          832.5977783203125,
          304.09393310546875
        ],
        [
          982.767822265625,
          352.88714599609375
        ],
        [
          970.902099609375,
          389.40606689453125
        ]
      ],
      "shape_type": "polygon",
      "flags": {}
    },
    {
      "label": "Brick",
      "line_color": null,
      "fill_color": null,
      "points": [
        [
          771.2320556640625,
          486.11285400390625
        ],
        [
          783.0977783203125,
          449.59393310546875
        ],
        [
          933.267822265625,
          498.38714599609375
        ],
        [
          921.402099609375,
          534.9060668945312
        ]
      ],
      "shape_type": "polygon",
      "flags": {}
    },
    {
      "label": "Brick",
      "line_color": null,
      "fill_color": null,
      "points": [
        [
          637.7249755859375,
          407.30169677734375
        ],
        [
          649.2255859375,
          371.90643310546875
        ],
        [
          794.7750244140625,
          419.19830322265625
        ],
        [
          783.2744140625,
          454.59356689453125
        ]
      ],
      "shape_type": "polygon",
      "flags": {}
    },
    {
      "label": "Brick",
      "line_color": null,
      "fill_color": null,
      "points": [
        [
          685.565185546875,
          264.5458068847656
        ],
        [
          695.823486328125,
          228.77073669433594
        ],
        [
          842.934814453125,
          270.9541931152344
        ],
        [
          832.676513671875,
          306.729248046875
        ]
      ],
      "shape_type": "polygon",
      "flags": {}
    },
    {
      "label": "Brick",
      "line_color": null,
      "fill_color": null,
      "points": [
        [
          760.7320556640625,
          522.1128540039062
        ],
        [
          772.5977783203125,
          485.59393310546875
        ],
        [
          922.767822265625,
          534.3871459960938
        ],
        [
          910.902099609375,
          570.9060668945312
        ]
      ],
      "shape_type": "polygon",
      "flags": {}
    },
    {
      "label": "Brick",
      "line_color": null,
      "fill_color": null,
      "points": [
        [
          648.2249755859375,
          368.30169677734375
        ],
        [
          659.7255859375,
          332.90643310546875
        ],
        [
          805.2750244140625,
          380.19830322265625
        ],
        [
          793.7744140625,
          415.59356689453125
        ]
      ],
      "shape_type": "polygon",
      "flags": {}
    },
    {
      "label": "Brick",
      "line_color": null,
      "fill_color": null,
      "points": [
        [
          613.5672607421875,
          479.9440612792969
        ],
        [
          625.8503401360545,
          445.578231292517
        ],
        [
          775.9327392578125,
          486.5559387207031
        ],
        [
          765.3487548828125,
          523.4666748046875
        ]
      ],
      "shape_type": "polygon",
      "flags": {}
    },
    {
      "label": "Brick",
      "line_color": null,
      "fill_color": null,
      "points": [
        [
          831.2320556640625,
          306.11285400390625
        ],
        [
          843.0977783203125,
          269.59393310546875
        ],
        [
          993.267822265625,
          318.38714599609375
        ],
        [
          981.402099609375,
          354.90606689453125
        ]
      ],
      "shape_type": "polygon",
      "flags": {}
    },
    {
      "label": "Brick",
      "line_color": null,
      "fill_color": null,
      "points": [
        [
          627.2108843537416,
          443.5374149659864
        ],
        [
          637.323486328125,
          408.7707214355469
        ],
        [
          784.434814453125,
          450.9541931152344
        ],
        [
          774.176513671875,
          486.7292785644531
        ]
      ],
      "shape_type": "polygon",
      "flags": {}
    },
    {
      "label": "Brick",
      "line_color": null,
      "fill_color": null,
      "points": [
        [
          783.2178955078125,
          448.49053955078125
        ],
        [
          794.3533935546875,
          414.21893310546875
        ],
        [
          935.2822265625,
          460.00946044921875
        ],
        [
          924.146728515625,
          494.28106689453125
        ]
      ],
      "shape_type": "polygon",
      "flags": {}
    }
  ],
  "lineColor": [
    0,
    255,
    0,
    128
  ],
  "fillColor": [
    255,
    0,
    0,
    128
  ],
  "imagePath": "OP_colorIMG_279.png",
  "imageData": null,
  "imageHeight": 720,
  "imageWidth": 1280
}