{
    "fillColor": [
        255,
        0,
        0,
        128
    ],
    "flags": {},
    "imageData": null,
    "imageHeight": 720,
    "imagePath": "OP_colorIMG_459.png",
    "imageWidth": 1280,
    "lineColor": [
        0,
        255,
        0,
        128
    ],
    "shapes": [
        {
            "fill_color": null,
            "flags": {},
            "label": "Brick",
            "line_color": null,
            "points": [
                [
                    863.9569091796875,
                    316.704833984375
                ],
                [
                    904.693359375,
                    315.28228759765625
                ],
                [
                    910.5430908203125,
                    482.795166015625
                ],
                [
                    869.806640625,
                    484.21771240234375
                ]
            ],
            "shape_type": "polygon"
        },
        {
            "fill_color": null,
            "flags": {},
            "label": "Brick",
            "line_color": null,
            "points": [
                [
                    805.1321411132813,
                    157.61195373535156
                ],
                [
                    844.6878051757813,
                    156.2306365966797
                ],
                [
                    850.3679809570313,
                    318.8880615234375
                ],
                [
                    810.8123168945313,
                    320.26934814453125
                ]
            ],
            "shape_type": "polygon"
        },
        {
            "fill_color": null,
            "flags": {},
            "label": "Brick",
            "line_color": null,
            "points": [
                [
                    850.4569091796875,
                    150.204833984375
                ],
                [
                    891.193359375,
                    148.78228759765625
                ],
                [
                    897.0430908203125,
                    316.295166015625
                ],
                [
                    856.306640625,
                    317.71771240234375
                ]
            ],
            "shape_type": "polygon"
        },
        {
            "fill_color": null,
            "flags": {},
            "label": "Brick",
            "line_color": null,
            "points": [
                [
                    819.0728759765625,
                    322.068359375
                ],
                [
                    859.73486328125,
                    319.2249755859375
                ],
                [
                    871.4271240234375,
                    486.431640625
                ],
                [
                    830.76513671875,
                    489.2750244140625
                ]
            ],
            "shape_type": "polygon"
        },
        {
            "fill_color": null,
            "flags": {},
            "label": "Brick",
            "line_color": null,
            "points": [
                [
                    673.0078735351563,
                    203.64749145507813
                ],
                [
                    706.6597290039063,
                    202.47232055664063
                ],
                [
                    711.4921264648438,
                    340.8525085449219
                ],
                [
                    677.8402709960938,
                    342.0276794433594
                ]
            ],
            "shape_type": "polygon"
        },
        {
            "fill_color": null,
            "flags": {},
            "label": "Brick",
            "line_color": null,
            "points": [
                [
                    902.9569091796875,
                    313.704833984375
                ],
                [
                    943.693359375,
                    312.28228759765625
                ],
                [
                    949.5430908203125,
                    479.795166015625
                ],
                [
                    908.806640625,
                    481.21771240234375
                ]
            ],
            "shape_type": "polygon"
        },
        {
            "fill_color": null,
            "flags": {},
            "label": "Brick",
            "line_color": null,
            "points": [
                [
                    944.6474609375,
                    426.4920654296875
                ],
                [
                    943.4722900390625,
                    392.84027099609375
                ],
                [
                    1081.8525390625,
                    388.0079345703125
                ],
                [
                    1083.0277099609375,
                    421.65972900390625
                ]
            ],
            "shape_type": "polygon"
        },
        {
            "fill_color": null,
            "flags": {},
            "label": "Brick",
            "line_color": null,
            "points": [
                [
                    901.612060546875,
                    316.3678894042969
                ],
                [
                    900.230712890625,
                    276.8122253417969
                ],
                [
                    1062.8880615234375,
                    271.1321105957031
                ],
                [
                    1064.2694091796875,
                    310.6877746582031
                ]
            ],
            "shape_type": "polygon"
        },
        {
            "fill_color": null,
            "flags": {},
            "label": "Brick",
            "line_color": null,
            "points": [
                [
                    938.6474609375,
                    349.9920654296875
                ],
                [
                    937.4722900390625,
                    316.34027099609375
                ],
                [
                    1075.8525390625,
                    311.5079345703125
                ],
                [
                    1077.0277099609375,
                    345.15972900390625
                ]
            ],
            "shape_type": "polygon"
        }
    ],
    "version": "3.21.1"
}
