{
  "version": "3.21.1",
  "flags": {},
  "shapes": [
    {
      "label": "Brick",
      "line_color": null,
      "fill_color": null,
      "points": [
        [
          762.8865979381444,
          404.63917525773195
        ],
        [
          756.7010309278351,
          371.1340206185567
        ],
        [
          905.1546391752578,
          335.0515463917526
        ],
        [
          913.9175257731958,
          371.1340206185567
        ]
      ],
      "shape_type": "polygon",
      "flags": {}
    },
    {
      "label": "Brick",
      "line_color": null,
      "fill_color": null,
      "points": [
        [
          901.5048828125,
          335.8174743652344
        ],
        [
          892.5013427734375,
          299.7062072753906
        ],
        [
          1042.2680412371135,
          265.97938144329896
        ],
        [
          1049.9986572265625,
          298.7937927246094
        ]
      ],
      "shape_type": "polygon",
      "flags": {}
    },
    {
      "label": "Brick",
      "line_color": null,
      "fill_color": null,
      "points": [
        [
          748.7711791992188,
          369.36114501953125
        ],
        [
          741.0333862304688,
          332.9576416015625
        ],
        [
          890.7288208007812,
          301.13885498046875
        ],
        [
          898.4666137695312,
          337.5423583984375
        ]
      ],
      "shape_type": "polygon",
      "flags": {}
    },
    {
      "label": "Brick",
      "line_color": null,
      "fill_color": null,
      "points": [
        [
          914.4329896907217,
          372.16494845360825
        ],
        [
          907.2164948453609,
          337.62886597938143
        ],
        [
          1058.7628865979382,
          304.12371134020617
        ],
        [
          1065.49853515625,
          335.7793273925781
        ]
      ],
      "shape_type": "polygon",
      "flags": {}
    },
    {
      "label": "Brick",
      "line_color": null,
      "fill_color": null,
      "points": [
        [
          742.7711791992188,
          331.86114501953125
        ],
        [
          735.0333862304688,
          295.4576416015625
        ],
        [
          884.7288208007812,
          263.63885498046875
        ],
        [
          892.4666137695312,
          300.0423583984375
        ]
      ],
      "shape_type": "polygon",
      "flags": {}
    },
    {
      "label": "Brick",
      "line_color": null,
      "fill_color": null,
      "points": [
        [
          883.5051546391753,
          262.88659793814435
        ],
        [
          1030.9278350515465,
          225.2577319587629
        ],
        [
          1041.7525773195875,
          257.7319587628866
        ],
        [
          892.2680412371134,
          297.42268041237116
        ]
      ],
      "shape_type": "polygon",
      "flags": {}
    },
    {
      "label": "Brick",
      "line_color": null,
      "fill_color": null,
      "points": [
        [
          772.1649484536083,
          443.29896907216494
        ],
        [
          764.4329896907217,
          408.2474226804124
        ],
        [
          911.8556701030928,
          373.1958762886598
        ],
        [
          920.6185567010309,
          409.7938144329897
        ]
      ],
      "shape_type": "polygon",
      "flags": {}
    }
  ],
  "lineColor": [
    0,
    255,
    0,
    128
  ],
  "fillColor": [
    255,
    0,
    0,
    128
  ],
  "imagePath": "OP_colorIMG_442.png",
  "imageData": null,
  "imageHeight": 720,
  "imageWidth": 1280
}