{
    "fillColor": [
        255,
        0,
        0,
        128
    ],
    "flags": {},
    "imageData": null,
    "imageHeight": 720,
    "imagePath": "OP_colorIMG_432.png",
    "imageWidth": 1280,
    "lineColor": [
        0,
        255,
        0,
        128
    ],
    "shapes": [
        {
            "fill_color": null,
            "flags": {},
            "label": "Brick",
            "line_color": null,
            "points": [
                [
                    910.6823120117188,
                    181.87216186523438
                ],
                [
                    942.5228881835938,
                    167.69583129882813
                ],
                [
                    1000.8175659179688,
                    298.6278381347656
                ],
                [
                    968.9769897460938,
                    312.8041687011719
                ]
            ],
            "shape_type": "polygon"
        },
        {
            "fill_color": null,
            "flags": {},
            "label": "Brick",
            "line_color": null,
            "points": [
                [
                    753.1823120117188,
                    261.3721618652344
                ],
                [
                    785.0228881835938,
                    247.19583129882813
                ],
                [
                    843.3175659179688,
                    378.1278381347656
                ],
                [
                    811.4769897460938,
                    392.3041687011719
                ]
            ],
            "shape_type": "polygon"
        },
        {
            "fill_color": null,
            "flags": {},
            "label": "Brick",
            "line_color": null,
            "points": [
                [
                    850.6823120117188,
                    213.37216186523438
                ],
                [
                    882.5228881835938,
                    199.19583129882813
                ],
                [
                    940.8175659179688,
                    330.1278381347656
                ],
                [
                    908.9769897460938,
                    344.3041687011719
                ]
            ],
            "shape_type": "polygon"
        },
        {
            "fill_color": null,
            "flags": {},
            "label": "Brick",
            "line_color": null,
            "points": [
                [
                    782.6724243164063,
                    249.48056030273438
                ],
                [
                    813.9988403320313,
                    234.20162963867188
                ],
                [
                    876.8274536132813,
                    363.0194396972656
                ],
                [
                    845.5010375976563,
                    378.2983703613281
                ]
            ],
            "shape_type": "polygon"
        },
        {
            "fill_color": null,
            "flags": {},
            "label": "Brick",
            "line_color": null,
            "points": [
                [
                    814.768310546875,
                    232.40493774414063
                ],
                [
                    845.0328369140625,
                    217.64395141601563
                ],
                [
                    905.731689453125,
                    342.0950622558594
                ],
                [
                    875.4671630859375,
                    356.8560485839844
                ]
            ],
            "shape_type": "polygon"
        },
        {
            "fill_color": null,
            "flags": {},
            "label": "Brick",
            "line_color": null,
            "points": [
                [
                    878.6724243164063,
                    199.98056030273438
                ],
                [
                    909.9988403320313,
                    184.70164489746094
                ],
                [
                    972.8274536132813,
                    313.5194396972656
                ],
                [
                    941.5010375976563,
                    328.79833984375
                ]
            ],
            "shape_type": "polygon"
        },
        {
            "fill_color": null,
            "flags": {},
            "label": "Brick",
            "line_color": null,
            "points": [
                [
                    943.6823120117188,
                    327.3721618652344
                ],
                [
                    975.5228881835938,
                    313.1958312988281
                ],
                [
                    1033.817626953125,
                    444.1278381347656
                ],
                [
                    1001.9769897460938,
                    458.3041687011719
                ]
            ],
            "shape_type": "polygon"
        },
        {
            "fill_color": null,
            "flags": {},
            "label": "Brick",
            "line_color": null,
            "points": [
                [
                    720.268310546875,
                    278.9049377441406
                ],
                [
                    750.5328369140625,
                    264.1439514160156
                ],
                [
                    811.231689453125,
                    388.5950622558594
                ],
                [
                    780.9671630859375,
                    403.3560485839844
                ]
            ],
            "shape_type": "polygon"
        },
        {
            "fill_color": null,
            "flags": {},
            "label": "Brick",
            "line_color": null,
            "points": [
                [
                    690.182373046875,
                    289.8721618652344
                ],
                [
                    722.02294921875,
                    275.6958312988281
                ],
                [
                    780.317626953125,
                    406.6278381347656
                ],
                [
                    748.47705078125,
                    420.8041687011719
                ]
            ],
            "shape_type": "polygon"
        },
        {
            "fill_color": null,
            "flags": {},
            "label": "Brick",
            "line_color": null,
            "points": [
                [
                    748.1724243164063,
                    421.9805603027344
                ],
                [
                    779.4988403320313,
                    406.7016296386719
                ],
                [
                    842.3274536132813,
                    535.5194091796875
                ],
                [
                    811.0010375976563,
                    550.79833984375
                ]
            ],
            "shape_type": "polygon"
        },
        {
            "fill_color": null,
            "flags": {},
            "label": "Brick",
            "line_color": null,
            "points": [
                [
                    908.0767211914063,
                    343.05615234375
                ],
                [
                    940.4650268554688,
                    327.25933837890625
                ],
                [
                    1005.4234008789063,
                    460.44384765625
                ],
                [
                    973.0350952148438,
                    476.24066162109375
                ]
            ],
            "shape_type": "polygon"
        },
        {
            "fill_color": null,
            "flags": {},
            "label": "Brick",
            "line_color": null,
            "points": [
                [
                    970.1724243164063,
                    313.9805603027344
                ],
                [
                    1001.498779296875,
                    298.7016296386719
                ],
                [
                    1064.327392578125,
                    427.5194396972656
                ],
                [
                    1033.0010986328125,
                    442.7983703613281
                ]
            ],
            "shape_type": "polygon"
        },
        {
            "fill_color": null,
            "flags": {},
            "label": "Brick",
            "line_color": null,
            "points": [
                [
                    630.1088256835938,
                    303.6560974121094
                ],
                [
                    619.7035522460938,
                    271.6318054199219
                ],
                [
                    751.3911743164063,
                    228.84390258789063
                ],
                [
                    761.7964477539063,
                    260.8681945800781
                ]
            ],
            "shape_type": "polygon"
        }
    ],
    "version": "3.21.1"
}
