{
  "version": "4.2.9",
  "flags": {},
  "shapes": [
    {
      "fill_color": null,
      "line_color": null,
      "label": "Brick",
      "points": [
        [
          634.3327026367188,
          325.8763122558594
        ],
        [
          667.2582397460938,
          296.2300109863281
        ],
        [
          789.1672973632812,
          431.6236877441406
        ],
        [
          756.2417602539062,
          461.2699890136719
        ]
      ],
      "group_id": null,
      "shape_type": "polygon",
      "flags": {}
    },
    {
      "fill_color": null,
      "line_color": null,
      "label": "Brick",
      "points": [
        [
          793.7681884765625,
          434.96630859375
        ],
        [
          824.7,
          406.7
        ],
        [
          952.731689453125,
          543.53369140625
        ],
        [
          918.9281005859375,
          573.9705200195312
        ]
      ],
      "group_id": null,
      "shape_type": "polygon",
      "flags": {}
    },
    {
      "fill_color": null,
      "line_color": null,
      "label": "Brick",
      "points": [
        [
          757.7681884765625,
          461.96636962890625
        ],
        [
          789.616935483871,
          433.1653225806452
        ],
        [
          916.731689453125,
          570.5336303710938
        ],
        [
          882.9281005859375,
          600.9705200195312
        ]
      ],
      "group_id": null,
      "shape_type": "polygon",
      "flags": {}
    },
    {
      "fill_color": null,
      "line_color": null,
      "label": "Brick",
      "points": [
        [
          740.1122019635344,
          234.7826086956522
        ],
        [
          772.3702664796634,
          208.55539971949509
        ],
        [
          894.0298507462686,
          341.79104477611935
        ],
        [
          863.1788079470199,
          368.8741721854305
        ]
      ],
      "group_id": null,
      "shape_type": "polygon",
      "flags": {}
    },
    {
      "fill_color": null,
      "line_color": null,
      "label": "Brick",
      "points": [
        [
          602.8327026367188,
          355.8763122558594
        ],
        [
          635.7582397460938,
          326.2300109863281
        ],
        [
          757.6672973632812,
          461.6236877441406
        ],
        [
          727.5,
          489.4
        ]
      ],
      "group_id": null,
      "shape_type": "polygon",
      "flags": {}
    },
    {
      "fill_color": null,
      "line_color": null,
      "label": "Brick",
      "points": [
        [
          569.8327026367188,
          384.3763122558594
        ],
        [
          602.7582397460938,
          354.7300109863281
        ],
        [
          727.3,
          490.2
        ],
        [
          696.1,
          519.4
        ]
      ],
      "group_id": null,
      "shape_type": "polygon",
      "flags": {}
    },
    {
      "fill_color": null,
      "line_color": null,
      "label": "Brick",
      "points": [
        [
          667.7682495117188,
          297.52601008628733
        ],
        [
          701.5718383789062,
          267.0891814730061
        ],
        [
          825.5597014925372,
          404.2910447761194
        ],
        [
          795.0604838709678,
          431.25
        ]
      ],
      "group_id": null,
      "shape_type": "polygon",
      "flags": {}
    },
    {
      "fill_color": null,
      "line_color": null,
      "label": "Brick",
      "points": [
        [
          704.8327026367188,
          262.8763122558594
        ],
        [
          737.5876577840112,
          237.30715287517532
        ],
        [
          860.5,
          369.4
        ],
        [
          828.5,
          398.6
        ]
      ],
      "group_id": null,
      "shape_type": "polygon",
      "flags": {}
    },
    {
      "fill_color": null,
      "line_color": null,
      "label": "Brick",
      "points": [
        [
          826.3,
          402.8
        ],
        [
          856.9,
          375.0
        ],
        [
          985.132382892057,
          512.9327902240326
        ],
        [
          951.1146850585938,
          542.6710205078125
        ]
      ],
      "group_id": null,
      "shape_type": "polygon",
      "flags": {}
    },
    {
      "fill_color": null,
      "line_color": null,
      "label": "Brick",
      "points": [
        [
          727.1,
          492.0
        ],
        [
          758.57177734375,
          463.02947998046875
        ],
        [
          883.731689453125,
          602.0336303710938
        ],
        [
          849.9281005859375,
          632.4705200195312
        ]
      ],
      "group_id": null,
      "shape_type": "polygon",
      "flags": {}
    },
    {
      "fill_color": null,
      "line_color": null,
      "label": "Brick",
      "points": [
        [
          696.7,
          523.5
        ],
        [
          727.07177734375,
          496.02947998046875
        ],
        [
          852.231689453125,
          635.0336303710938
        ],
        [
          818.4281005859375,
          665.4705200195312
        ]
      ],
      "group_id": null,
      "shape_type": "polygon",
      "flags": {}
    },
    {
      "fill_color": null,
      "line_color": null,
      "label": "Brick",
      "points": [
        [
          776.577840112202,
          207.85413744740532
        ],
        [
          806.3113604488078,
          179.6633941093969
        ],
        [
          929.6019900497512,
          313.93034825870643
        ],
        [
          898.5945434570312,
          341.1669921875
        ]
      ],
      "group_id": null,
      "shape_type": "polygon",
      "flags": {}
    },
    {
      "fill_color": null,
      "line_color": null,
      "label": "Brick",
      "points": [
        [
          539.8327026367188,
          417.3763122558594
        ],
        [
          572.7582397460938,
          387.7300109863281
        ],
        [
          695.7,
          524.9
        ],
        [
          661.7417602539062,
          552.77001953125
        ]
      ],
      "group_id": null,
      "shape_type": "polygon",
      "flags": {}
    },
    {
      "fill_color": null,
      "line_color": null,
      "label": "Brick",
      "points": [
        [
          662.5,
          557.5
        ],
        [
          693.7,
          528.8
        ],
        [
          822.2962036132812,
          667.443603515625
        ],
        [
          787.6146850585938,
          698.6710205078125
        ]
      ],
      "group_id": null,
      "shape_type": "polygon",
      "flags": {}
    },
    {
      "label": "Brick",
      "points": [
        [
          989.0066225165563,
          509.5364238410596
        ],
        [
          1020.2649006622516,
          481.3245033112583
        ],
        [
          895.2317880794702,
          343.97350993377484
        ],
        [
          862.6490066225166,
          372.317880794702
        ]
      ],
      "group_id": null,
      "shape_type": "polygon",
      "flags": {}
    }
  ],
  "imagePath": "OP_colorIMG_314.png",
  "imageData": null,
  "imageHeight": 720,
  "imageWidth": 1280,
  "fillColor": [
    255,
    0,
    0,
    128
  ],
  "lineColor": [
    0,
    255,
    0,
    128
  ]
}