{
  "version": "4.2.9",
  "flags": {},
  "shapes": [
    {
      "line_color": null,
      "fill_color": null,
      "label": "Brick",
      "points": [
        [
          828.2671508789062,
          375.650146484375
        ],
        [
          859.4920043945312,
          349.4493408203125
        ],
        [
          967.2328491210938,
          477.849853515625
        ],
        [
          936.0079956054688,
          504.0506591796875
        ]
      ],
      "group_id": null,
      "shape_type": "polygon",
      "flags": {}
    },
    {
      "line_color": null,
      "fill_color": null,
      "label": "Brick",
      "points": [
        [
          891.7530517578125,
          319.66900634765625
        ],
        [
          923.883056640625,
          292.708740234375
        ],
        [
          1034.746826171875,
          424.83099365234375
        ],
        [
          1002.6168212890625,
          451.791259765625
        ]
      ],
      "group_id": null,
      "shape_type": "polygon",
      "flags": {}
    },
    {
      "line_color": null,
      "fill_color": null,
      "label": "Brick",
      "points": [
        [
          860.8247422680413,
          349.4845360824742
        ],
        [
          893.8144329896908,
          320.1030927835052
        ],
        [
          1003.27490234375,
          450.7933349609375
        ],
        [
          969.334716796875,
          479.2724609375
        ]
      ],
      "group_id": null,
      "shape_type": "polygon",
      "flags": {}
    },
    {
      "line_color": null,
      "fill_color": null,
      "label": "Brick",
      "points": [
        [
          794.3298969072165,
          400.0
        ],
        [
          829.3814432989691,
          374.74226804123714
        ],
        [
          937.2609252929688,
          502.3121337890625
        ],
        [
          904.2258911132812,
          530.0318603515625
        ]
      ],
      "group_id": null,
      "shape_type": "polygon",
      "flags": {}
    },
    {
      "line_color": null,
      "fill_color": null,
      "label": "Brick",
      "points": [
        [
          731.4432989690722,
          455.1546391752577
        ],
        [
          760.3092783505155,
          428.8659793814433
        ],
        [
          873.1958762886599,
          560.3092783505155
        ],
        [
          844.3298969072165,
          588.1443298969073
        ]
      ],
      "group_id": null,
      "shape_type": "polygon",
      "flags": {}
    },
    {
      "line_color": null,
      "fill_color": null,
      "label": "Brick",
      "points": [
        [
          926.6317138671875,
          293.205810546875
        ],
        [
          959.6829833984375,
          267.38330078125
        ],
        [
          1065.8681640625,
          403.294189453125
        ],
        [
          1032.81689453125,
          429.11669921875
        ]
      ],
      "group_id": null,
      "shape_type": "polygon",
      "flags": {}
    },
    {
      "line_color": null,
      "fill_color": null,
      "label": "Brick",
      "points": [
        [
          762.3711340206186,
          424.22680412371136
        ],
        [
          792.2680412371134,
          402.0618556701031
        ],
        [
          905.6701030927835,
          530.9278350515464
        ],
        [
          876.2886597938144,
          557.7319587628866
        ]
      ],
      "group_id": null,
      "shape_type": "polygon",
      "flags": {}
    }
  ],
  "imagePath": "OP_colorIMG_207.png",
  "imageData": null,
  "imageHeight": 720,
  "imageWidth": 1280,
  "lineColor": [
    0,
    255,
    0,
    128
  ],
  "fillColor": [
    255,
    0,
    0,
    128
  ]
}