{
  "version": "4.2.9",
  "flags": {},
  "shapes": [
    {
      "fill_color": null,
      "line_color": null,
      "label": "Brick",
      "points": [
        [
          761.5477629987909,
          369.52841596130594
        ],
        [
          725.2720677146312,
          349.21402660217655
        ],
        [
          819.2363891601562,
          193.75775146484375
        ],
        [
          856.8097534179688,
          217.2362060546875
        ]
      ],
      "group_id": null,
      "shape_type": "polygon",
      "flags": {}
    },
    {
      "fill_color": null,
      "line_color": null,
      "label": "Brick",
      "points": [
        [
          847.5432739257812,
          417.0823059082031
        ],
        [
          808.4236450195312,
          396.2820739746094
        ],
        [
          897.9959919839679,
          238.1763527054108
        ],
        [
          934.6693386773546,
          258.11623246492985
        ]
      ],
      "group_id": null,
      "shape_type": "polygon",
      "flags": {}
    },
    {
      "fill_color": null,
      "line_color": null,
      "label": "Brick",
      "points": [
        [
          805.3873901367188,
          395.2170715332031
        ],
        [
          767.0175170898438,
          373.0642395019531
        ],
        [
          861.7234468937876,
          219.83967935871743
        ],
        [
          896.4824829101562,
          237.43576049804688
        ]
      ],
      "group_id": null,
      "shape_type": "polygon",
      "flags": {}
    },
    {
      "fill_color": null,
      "line_color": null,
      "label": "Brick",
      "points": [
        [
          928.5432739257812,
          460.5823059082031
        ],
        [
          889.4236450195312,
          439.7820739746094
        ],
        [
          974.9567260742188,
          278.9176940917969
        ],
        [
          1014.0763549804688,
          299.7179260253906
        ]
      ],
      "group_id": null,
      "shape_type": "polygon",
      "flags": {}
    },
    {
      "fill_color": null,
      "line_color": null,
      "label": "Brick",
      "points": [
        [
          968.1047765793528,
          483.5130970724191
        ],
        [
          929.9236450195312,
          463.7820739746094
        ],
        [
          1015.4567260742188,
          302.9176940917969
        ],
        [
          1054.576416015625,
          323.7179260253906
        ]
      ],
      "group_id": null,
      "shape_type": "polygon",
      "flags": {}
    },
    {
      "fill_color": null,
      "line_color": null,
      "label": "Brick",
      "points": [
        [
          883.684326171875,
          443.6162109375
        ],
        [
          844.291259765625,
          420.87261962890625
        ],
        [
          937.8155517578125,
          258.8837890625
        ],
        [
          977.2086181640625,
          281.62738037109375
        ]
      ],
      "group_id": null,
      "shape_type": "polygon",
      "flags": {}
    },
    {
      "fill_color": null,
      "line_color": null,
      "label": "Brick",
      "points": [
        [
          1005.7010785824344,
          507.3959938366718
        ],
        [
          968.7211093990754,
          487.05701078582433
        ],
        [
          1058.4320066478476,
          324.770537906876
        ],
        [
          1097.8250730540976,
          347.5141292154697
        ]
      ],
      "group_id": null,
      "shape_type": "polygon",
      "flags": {}
    },
    {
      "fill_color": null,
      "line_color": null,
      "label": "Brick",
      "points": [
        [
          722.7636108398438,
          344.74224853515625
        ],
        [
          685.1902465820312,
          321.2637939453125
        ],
        [
          781.7363891601562,
          166.75775146484375
        ],
        [
          819.3097534179688,
          190.2362060546875
        ]
      ],
      "group_id": null,
      "shape_type": "polygon",
      "flags": {}
    },
    {
      "fill_color": null,
      "line_color": null,
      "label": "Brick",
      "points": [
        [
          714.9253731343283,
          554.3710021321962
        ],
        [
          678.2515991471215,
          533.2622601279318
        ],
        [
          764.6219686162625,
          374.32239657631953
        ],
        [
          801.7118402282454,
          395.5777460770328
        ]
      ],
      "group_id": null,
      "shape_type": "polygon",
      "flags": {}
    },
    {
      "fill_color": null,
      "line_color": null,
      "label": "Brick",
      "points": [
        [
          676.5458422174839,
          531.1300639658848
        ],
        [
          639.8720682302771,
          508.955223880597
        ],
        [
          724.304715840387,
          352.96251511487304
        ],
        [
          762.7569528415962,
          372.9141475211608
        ]
      ],
      "group_id": null,
      "shape_type": "polygon",
      "flags": {}
    },
    {
      "fill_color": null,
      "line_color": null,
      "label": "Brick",
      "points": [
        [
          754.3668145757697,
          575.1938249550187
        ],
        [
          717.6930405885629,
          554.0850829507544
        ],
        [
          804.0634100577039,
          395.1452193991423
        ],
        [
          841.1532816696867,
          416.4005688998556
        ]
      ],
      "group_id": null,
      "shape_type": "polygon",
      "flags": {}
    },
    {
      "fill_color": null,
      "line_color": null,
      "label": "Brick",
      "points": [
        [
          640.3116079832497,
          505.4063402421611
        ],
        [
          603.6378339960429,
          483.23150015687327
        ],
        [
          688.0704816061527,
          327.23879139114933
        ],
        [
          726.522718607362,
          347.1904237974371
        ]
      ],
      "group_id": null,
      "shape_type": "polygon",
      "flags": {}
    }
  ],
  "imagePath": "OP_colorIMG_144.png",
  "imageData": null,
  "imageHeight": 720,
  "imageWidth": 1280,
  "fillColor": [
    255,
    0,
    0,
    128
  ],
  "lineColor": [
    0,
    255,
    0,
    128
  ]
}