{
  "version": "4.2.9",
  "flags": {},
  "shapes": [
    {
      "label": "Brick",
      "points": [
        [
          830.716723549488,
          629.0102389078498
        ],
        [
          861.0921501706484,
          659.0443686006826
        ],
        [
          980.2047781569966,
          517.7474402730376
        ],
        [
          945.3924914675767,
          491.8088737201365
        ]
      ],
      "group_id": null,
      "shape_type": "polygon",
      "flags": {}
    },
    {
      "label": "Brick",
      "points": [
        [
          949.8293515358362,
          488.0546075085324
        ],
        [
          1073.037542662116,
          352.21843003412965
        ],
        [
          1105.1194539249145,
          380.5460750853242
        ],
        [
          980.2047781569966,
          514.334470989761
        ]
      ],
      "group_id": null,
      "shape_type": "polygon",
      "flags": {}
    },
    {
      "label": "Brick",
      "points": [
        [
          819.4539249146757,
          632.0819112627986
        ],
        [
          938.5665529010238,
          487.3720136518771
        ],
        [
          904.4368600682593,
          459.72696245733783
        ],
        [
          788.3959044368601,
          604.0955631399318
        ]
      ],
      "group_id": null,
      "shape_type": "polygon",
      "flags": {}
    },
    {
      "label": "Brick",
      "points": [
        [
          912.9692832764505,
          459.04436860068256
        ],
        [
          1034.8122866894198,
          323.20819112627987
        ],
        [
          1065.8703071672355,
          351.87713310580205
        ],
        [
          945.0511945392491,
          487.71331058020473
        ]
      ],
      "group_id": null,
      "shape_type": "polygon",
      "flags": {}
    },
    {
      "label": "Brick",
      "points": [
        [
          1000.3412969283276,
          292.15017064846415
        ],
        [
          1033.7883959044368,
          317.7474402730375
        ],
        [
          909.8976109215016,
          454.9488054607508
        ],
        [
          879.5221843003412,
          427.98634812286684
        ]
      ],
      "group_id": null,
      "shape_type": "polygon",
      "flags": {}
    },
    {
      "label": "Brick",
      "points": [
        [
          873.7201365187713,
          426.6211604095563
        ],
        [
          906.4846416382252,
          453.92491467576787
        ],
        [
          787.0307167235494,
          591.8088737201365
        ],
        [
          753.9249146757679,
          562.1160409556313
        ]
      ],
      "group_id": null,
      "shape_type": "polygon",
      "flags": {}
    },
    {
      "label": "Brick",
      "points": [
        [
          718.0887372013651,
          531.0580204778157
        ],
        [
          842.320819112628,
          397.2696245733788
        ],
        [
          873.7201365187713,
          424.23208191126275
        ],
        [
          752.2184300341296,
          560.0682593856654
        ]
      ],
      "group_id": null,
      "shape_type": "polygon",
      "flags": {}
    },
    {
      "label": "Brick",
      "points": [
        [
          845.7337883959044,
          396.9283276450512
        ],
        [
          966.5529010238907,
          262.45733788395904
        ],
        [
          998.6348122866893,
          287.3720136518771
        ],
        [
          876.4505119453925,
          426.27986348122863
        ]
      ],
      "group_id": null,
      "shape_type": "polygon",
      "flags": {}
    },
    {
      "label": "Brick",
      "points": [
        [
          812.2866894197952,
          366.8941979522184
        ],
        [
          932.4232081911263,
          231.0580204778157
        ],
        [
          965.8703071672354,
          258.70307167235495
        ],
        [
          844.3686006825939,
          393.5153583617747
        ]
      ],
      "group_id": null,
      "shape_type": "polygon",
      "flags": {}
    },
    {
      "label": "Brick",
      "points": [
        [
          776.1092150170648,
          334.47098976109214
        ],
        [
          900.3412969283276,
          204.43686006825936
        ],
        [
          929.0102389078497,
          232.08191126279863
        ],
        [
          807.5085324232082,
          365.5290102389078
        ]
      ],
      "group_id": null,
      "shape_type": "polygon",
      "flags": {}
    },
    {
      "label": "Brick",
      "points": [
        [
          740.6143344709898,
          304.77815699658703
        ],
        [
          865.5290102389079,
          174.40273037542661
        ],
        [
          895.5631399317406,
          199.3174061433447
        ],
        [
          771.3310580204778,
          332.0819112627986
        ]
      ],
      "group_id": null,
      "shape_type": "polygon",
      "flags": {}
    },
    {
      "label": "Brick",
      "points": [
        [
          711.2627986348123,
          270.98976109215016
        ],
        [
          836.1774744027304,
          141.29692832764505
        ],
        [
          864.8464163822525,
          171.3310580204778
        ],
        [
          738.5665529010239,
          299.65870307167233
        ]
      ],
      "group_id": null,
      "shape_type": "polygon",
      "flags": {}
    },
    {
      "label": "Brick",
      "points": [
        [
          707.1672354948805,
          274.74402730375425
        ],
        [
          739.9317406143344,
          303.0716723549488
        ],
        [
          622.5255972696245,
          440.2730375426621
        ],
        [
          589.0784982935153,
          410.580204778157
        ]
      ],
      "group_id": null,
      "shape_type": "polygon",
      "flags": {}
    },
    {
      "label": "Brick",
      "points": [
        [
          621.8430034129692,
          443.68600682593853
        ],
        [
          652.5597269624573,
          470.98976109215016
        ],
        [
          770.6484641638225,
          335.8361774744027
        ],
        [
          738.5665529010239,
          307.84982935153585
        ]
      ],
      "group_id": null,
      "shape_type": "polygon",
      "flags": {}
    },
    {
      "label": "Brick",
      "points": [
        [
          655.9726962457338,
          474.4027303754266
        ],
        [
          772.6962457337884,
          337.88395904436857
        ],
        [
          802.7303754266211,
          364.5051194539249
        ],
        [
          683.9590443686006,
          501.36518771331055
        ]
      ],
      "group_id": null,
      "shape_type": "polygon",
      "flags": {}
    },
    {
      "label": "Brick",
      "points": [
        [
          686.0068259385665,
          504.77815699658703
        ],
        [
          804.778156996587,
          368.6006825938566
        ],
        [
          835.494880546075,
          392.49146757679176
        ],
        [
          718.0887372013651,
          533.1058020477816
        ]
      ],
      "group_id": null,
      "shape_type": "polygon",
      "flags": {}
    }
  ],
  "imagePath": "OP_colorIMG_181.png",
  "imageData": null,
  "imageHeight": 720,
  "imageWidth": 1280
}